[
    {
        "ParameterKey": "AvailabilityZones",
        "ParameterValue": "$[taskcat_genaz_2]"
    },
    {
        "ParameterKey": "InstanceType",
        "ParameterValue": "t2.large"
    },
    {
        "ParameterKey": "KeyPairName",
        "ParameterValue": "tonynv"
    },
    {
        "ParameterKey": "NumberOfAZs",
        "ParameterValue": "2"
    },
    {
        "ParameterKey": "PublicSubnet1CIDR",
        "ParameterValue": "10.0.128.0/20"
    },
    {
        "ParameterKey": "PublicSubnet2CIDR",
        "ParameterValue": "10.0.144.0/20"
    },
    {
        "ParameterKey": "QSS3BucketName",
        "ParameterValue": "$[taskcat_autobucket]"
    },
    {
        "ParameterKey": "RemoteAccessCIDR",
        "ParameterValue": "0.0.0.0/0"
    },
    {
        "ParameterKey": "BlockChainAccessCIDR",
        "ParameterValue": "0.0.0.0/0"
    },
    {
        "ParameterKey": "VPCCIDR",
        "ParameterValue": "10.0.0.0/16"
    }
]